README.md
setup.py
test_prasadi/__init__.py
test_prasadi.egg-info/PKG-INFO
test_prasadi.egg-info/SOURCES.txt
test_prasadi.egg-info/dependency_links.txt
test_prasadi.egg-info/entry_points.txt
test_prasadi.egg-info/requires.txt
test_prasadi.egg-info/top_level.txt