Metadata-Version: 2.1
Name: test-prasadi
Version: 1.0
Summary: Novigi Custom Airflow Operators
Home-page: https://Prasadi1994@bitbucket.org/novigi/novigi_operators.git
Author: Novigi
Author-email: prasadi19943@gmail.com
License: Apache License 2.0
Platform: UNKNOWN
Requires-Python: >=3.6
